.gitignore
.readthedocs.yml
AUTHORS
LICENSE
README.rst
TODO.rst
dev_requirements.txt
setup.py
docs/Makefile
docs/environment.yml
docs/requirements.txt
docs/source/api.rst
docs/source/conf.py
docs/source/index.rst
docs/source/internal.rst
src/xactor/__init__.py
src/xactor/actor_proxy.py
src/xactor/actor_system.py
src/xactor/evars.py
src/xactor/message.py
src/xactor/mpi_acomm.py
src/xactor/mpi_rank_actor.py
src/xactor.egg-info/PKG-INFO
src/xactor.egg-info/SOURCES.txt
src/xactor.egg-info/dependency_links.txt
src/xactor.egg-info/requires.txt
src/xactor.egg-info/top_level.txt
tests/test_scripts.py
tests/scripts/check_latency.py
tests/scripts/check_throughput.py
tests/scripts/fanout.py
tests/scripts/hello.py
tests/scripts/npbuf.py